{
  "years_of_duty": {
    "data": {
      "От 2 до 5 лет": 0.1,
      "От 5 до 10 лет": 0.15,
      "От 10 до 15 лет": 0.2,
      "От 15 до 20 лет": 0.25,
      "От 20 до 25 лет": 0.3,
      "От 25 лет и более": 0.4
    },
    "name": "Надбавка за стаж службы (выслугу лет)",
    "payment_name": "Надбавка за стаж службы (выслугу лет)",
    "description": "",
    "document_id": 6,
    "salary": true,
    "pension": true,
    "apply_to": ["Занимаемая должность", "Специальное звание"]
  },
  "class": {
    "data": {
      "специалиста третьего класса": 0.05,
      "специалиста второго класса": 0.1,
      "специалист первого класса": 0.2,
      "мастер (высшее квалификационное звание)": 0.3
    },
    "name": "Квалификационное звание",
    "payment_name": "Доплата за квалификационное звание",
    "description": "",
    "document_id": 6,
    "salary": true,
    "pension": false,
    "apply_to": ["Занимаемая должность"]
  },
  "science_degree": {
    "data": {
      "кандидат наук": 0.15,
      "доктор наук": 0.3
    },
    "name": "Ученая степень",
    "payment_name": "Доплата за ученую степень",
    "description": "",
    "document_id": 5,
    "salary": true,
    "pension": false,
    "apply_to": ["Занимаемая должность"]
  },
  "science_rank": {
    "data": {
      "доцент, старший научный сотрудник": 0.1,
      "профессор": 0.25
    },
    "name": "Ученое звание",
    "payment_name": "Доплата за ученое звание",
    "description": "",
    "document_id": 5,
    "salary": true,
    "pension": false,
    "apply_to": ["Занимаемая должность"]
  },
  "sport_rank": {
    "data": {
      "кандидат в мастера спорта": 0.05,
      "мастер спорта": 0.08,
      "мастер спорта международного класса": 0.1,
      "заслуженный мастер спорта": 0.15
    },
    "name": "Спортивный разряд, звание",
    "payment_name": "Доплата за спортивный разряд, звание",
    "description": "",
    "document_id": 5,
    "salary": true,
    "pension": false,
    "apply_to": ["Занимаемая должность"]
  },
  "secrecy": {
    "data": {
      "секретно": 0.1,
      "совершенно секретно": 0.2
    },
    "name": "Доступ к гос. тайне",
    "payment_name": "Надбавка за работу со сведениями, сост. гос. тайну",
    "description": "",
    "document_id": 4,
    "salary": true,
    "pension": false,
    "apply_to": ["Занимаемая должность"]
  },
  "staff_job": {
    "data": {
      "заместителя начальника образовательной организации": 0.3,
      "начальника образовательной организации": 0.4
    },
    "name": "Замещение руководящей должности",
      "payment_name": "Надбавка за замещение руководящей должности",
      "description": "",
      "document_id": 5,
      "salary": true,
      "pension": false,
      "apply_to": ["Занимаемая должность"]
  },
  "secrecy_job": {
    "data": {
      "от 1 года до 5 лет": 0.1,
      "от 5 до 10 лет": 0.15,
      "от 10 лет и выше": 0.2
    },
    "name": "Стаж работы в струк. подр. по защите гос. тайны",
      "payment_name": "Надбавка за стаж работы в струк. подр. по защите гос. тайны",
      "description": "",
      "document_id": 6,
      "salary": true,
      "pension": false,
      "apply_to": ["Занимаемая должность"]
  }
}